noted/NoteGrid.py
noted/NotedItem.py
noted/__init__.py
noted/__main__.py
noted/noted.py
noted/note_data/notes.json
noted_notes-0.1.4.dist-info/LICENSE
noted_notes-0.1.4.dist-info/METADATA
noted_notes-0.1.4.dist-info/WHEEL
noted_notes-0.1.4.dist-info/entry_points.txt
noted_notes-0.1.4.dist-info/top_level.txt
noted_notes-0.1.4.dist-info/RECORD
